odoo/addons/l10n_pt_vat/README.rst
odoo/addons/l10n_pt_vat/__init__.py
odoo/addons/l10n_pt_vat/__manifest__.py
odoo/addons/l10n_pt_vat/data/account_tax.xml
odoo/addons/l10n_pt_vat/data/vat_adjustment_norm.xml
odoo/addons/l10n_pt_vat/i18n/pt.po
odoo/addons/l10n_pt_vat/models/__init__.py
odoo/addons/l10n_pt_vat/models/account_invoice.py
odoo/addons/l10n_pt_vat/models/account_journal.py
odoo/addons/l10n_pt_vat/models/account_tax.py
odoo/addons/l10n_pt_vat/models/vat_adjustment_norm.py
odoo/addons/l10n_pt_vat/readme/CONFIGURATION.rst
odoo/addons/l10n_pt_vat/readme/CONTRIBUTORS.rst
odoo/addons/l10n_pt_vat/readme/DESCRIPTION.rst
odoo/addons/l10n_pt_vat/readme/USAGE.rst
odoo/addons/l10n_pt_vat/security/ir.model.access.csv
odoo/addons/l10n_pt_vat/static/description/icon.png
odoo/addons/l10n_pt_vat/static/description/index.html
odoo/addons/l10n_pt_vat/views/account_invoice_view.xml
odoo/addons/l10n_pt_vat/views/vat_adjustment_norm_view.xml
odoo12_addon_l10n_pt_vat-12.0.0.3.0.dist-info/METADATA
odoo12_addon_l10n_pt_vat-12.0.0.3.0.dist-info/WHEEL
odoo12_addon_l10n_pt_vat-12.0.0.3.0.dist-info/top_level.txt
odoo12_addon_l10n_pt_vat-12.0.0.3.0.dist-info/RECORD
