Metadata-Version: 2.1
Name: odoo12-addon-l10n-pt-vat
Version: 12.0.0.3.0
Summary: Portuguese VAT requirements extensions
Home-page: https://github.com/OCA/l10n-portugal
Author: Sossia, Odoo Community Association (OCA)
Author-email: support@odoo-community.org
License: AGPL-3
Platform: UNKNOWN
Classifier: Programming Language :: Python
Classifier: Framework :: Odoo
Classifier: License :: OSI Approved :: GNU Affero General Public License v3
Requires-Python: >=3.5
Requires-Dist: odoo (<12.1dev,>=12.0a)
